odoo8_addon_shopinvader_claim-8.0.1.0.0.99.dev15-py3.8-nspkg.pth
odoo_addons/shopinvader_claim/README.rst
odoo_addons/shopinvader_claim/__init__.py
odoo_addons/shopinvader_claim/__openerp__.py
odoo_addons/shopinvader_claim/controllers/__init__.py
odoo_addons/shopinvader_claim/controllers/main.py
odoo_addons/shopinvader_claim/demo/claim_demo.xml
odoo_addons/shopinvader_claim/i18n/fr.po
odoo_addons/shopinvader_claim/models/__init__.py
odoo_addons/shopinvader_claim/models/claim.py
odoo_addons/shopinvader_claim/models/notification.py
odoo_addons/shopinvader_claim/services/__init__.py
odoo_addons/shopinvader_claim/services/claim.py
odoo_addons/shopinvader_claim/tests/__init__.py
odoo_addons/shopinvader_claim/tests/test_claim.py
odoo8_addon_shopinvader_claim-8.0.1.0.0.99.dev15.dist-info/METADATA
odoo8_addon_shopinvader_claim-8.0.1.0.0.99.dev15.dist-info/WHEEL
odoo8_addon_shopinvader_claim-8.0.1.0.0.99.dev15.dist-info/namespace_packages.txt
odoo8_addon_shopinvader_claim-8.0.1.0.0.99.dev15.dist-info/top_level.txt
odoo8_addon_shopinvader_claim-8.0.1.0.0.99.dev15.dist-info/RECORD
