Metadata-Version: 2.1
Name: odoo8-addon-shopinvader-claim
Version: 8.0.1.0.0.99.dev15
Summary: Shopinvader Claim Management
Home-page: https://akretion.com
Author: Akretion
License: AGPL-3
Platform: UNKNOWN
Classifier: Programming Language :: Python
Classifier: Framework :: Odoo
Classifier: Framework :: Odoo :: 8.0
Classifier: License :: OSI Approved :: GNU Affero General Public License v3
Requires-Python: ~=2.7
Requires-Dist: odoo8-addon-crm-claim-rma
Requires-Dist: odoo8-addon-onchange-helper
Requires-Dist: odoo8-addon-shopinvader
Requires-Dist: odoo (<9.0a,>=8.0a)
